INSTALL.rst
LICENSE
MANIFEST.in
README.rst
VERSION
requirements.txt
setup.cfg
setup.py
tasks.py
src/sulfur/__init__.py
src/sulfur/__meta__.py
src/sulfur/all.py
src/sulfur/client.py
src/sulfur/conversions.py
src/sulfur/delayed.py
src/sulfur/django.py
src/sulfur/driver.py
src/sulfur/driver_attributes.py
src/sulfur/element.py
src/sulfur/env.py
src/sulfur/errors.py
src/sulfur/id_manager.py
src/sulfur/queriable.py
src/sulfur/queryset.py
src/sulfur/response.py
src/sulfur/simplehtml5.py
src/sulfur/testserver.py
src/sulfur/urlchecker.py
src/sulfur/urlcheckerclient.py
src/sulfur/utils.py
src/sulfur/validators.py
src/sulfur.egg-info/PKG-INFO
src/sulfur.egg-info/SOURCES.txt
src/sulfur.egg-info/dependency_links.txt
src/sulfur.egg-info/entry_points.txt
src/sulfur.egg-info/not-zip-safe
src/sulfur.egg-info/requires.txt
src/sulfur.egg-info/top_level.txt
src/sulfur/tests/__init__.py
src/sulfur/tests/__main__.py
src/sulfur/tests/conftest.py
src/sulfur/tests/test_client.py
src/sulfur/tests/test_conversions.py
src/sulfur/tests/test_delayed.py
src/sulfur/tests/test_documentation.py
src/sulfur/tests/test_driver.py
src/sulfur/tests/test_element.py
src/sulfur/tests/test_queriable.py
src/sulfur/tests/test_queryset.py
src/sulfur/tests/test_server.py
src/sulfur/tests/test_simplehtml5.py
src/sulfur/tests/test_urlchecker.py
src/sulfur/tests/utils.py
src/sulfur_plugin/__init__.py
src/sulfur_plugin/pytest.py